{
  "last_updated": "2026-06-27T07:06:02Z",
  "source": "tank-ono.cz + mbenzin.cz + ccs.cz + orlen.cz + omv.cz + fuelto.net + ipumpuj.cz + shell.cz + mol.cz + benzina.cz",
  "averages": {
    "petrol_95": 39.45,
    "diesel": 37.11
  },
  "stations": [
    {
      "name": "Praha",
      "chain": "Ostatní",
      "city": "",
      "region": "Praha",
      "address": "",
      "petrol_95": 39.87,
      "diesel": 36.69,
      "last_updated": "2026-06-27",
      "id": 1
    },
    {
      "name": "Středočeský kraj",
      "chain": "Ostatní",
      "city": "",
      "region": "Neznámý kraj",
      "address": "",
      "petrol_95": 39.55,
      "diesel": 36.94,
      "last_updated": "2026-06-27",
      "id": 2
    },
    {
      "name": "Moravskoslezský kraj",
      "chain": "Ostatní",
      "city": "",
      "region": "Neznámý kraj",
      "address": "",
      "petrol_95": 39.26,
      "diesel": 36.91,
      "last_updated": "2026-06-27",
      "id": 3
    },
    {
      "name": "Jihomoravský kraj",
      "chain": "Ostatní",
      "city": "",
      "region": "Neznámý kraj",
      "address": "",
      "petrol_95": 39.75,
      "diesel": 37.28,
      "last_updated": "2026-06-27",
      "id": 4
    },
    {
      "name": "Ústecký kraj",
      "chain": "Ostatní",
      "city": "",
      "region": "Neznámý kraj",
      "address": "",
      "petrol_95": 39.27,
      "diesel": 36.95,
      "last_updated": "2026-06-27",
      "id": 5
    },
    {
      "name": "Olomoucký kraj",
      "chain": "Ostatní",
      "city": "",
      "region": "Olomoucký",
      "address": "",
      "petrol_95": 39.48,
      "diesel": 37.46,
      "last_updated": "2026-06-27",
      "id": 6
    },
    {
      "name": "Jihočeský kraj",
      "chain": "Ostatní",
      "city": "",
      "region": "Neznámý kraj",
      "address": "",
      "petrol_95": 39.46,
      "diesel": 37.53,
      "last_updated": "2026-06-27",
      "id": 7
    },
    {
      "name": "Plzeňský kraj",
      "chain": "Ostatní",
      "city": "",
      "region": "Plzeňský",
      "address": "",
      "petrol_95": 39.67,
      "diesel": 37.66,
      "last_updated": "2026-06-27",
      "id": 8
    },
    {
      "name": "Karlovarský kraj",
      "chain": "Ostatní",
      "city": "",
      "region": "Neznámý kraj",
      "address": "",
      "petrol_95": 39.53,
      "diesel": 37.06,
      "last_updated": "2026-06-27",
      "id": 9
    },
    {
      "name": "Liberecký kraj",
      "chain": "Ostatní",
      "city": "",
      "region": "Liberecký",
      "address": "",
      "petrol_95": 39.49,
      "diesel": 37.24,
      "last_updated": "2026-06-27",
      "id": 10
    },
    {
      "name": "Královehradecký kraj",
      "chain": "Ostatní",
      "city": "",
      "region": "Neznámý kraj",
      "address": "",
      "petrol_95": 39.06,
      "diesel": 36.37,
      "last_updated": "2026-06-27",
      "id": 11
    },
    {
      "name": "Pardubický kraj",
      "chain": "Ostatní",
      "city": "",
      "region": "Neznámý kraj",
      "address": "",
      "petrol_95": 39.37,
      "diesel": 37.03,
      "last_updated": "2026-06-27",
      "id": 12
    },
    {
      "name": "Kraj Vysočina",
      "chain": "Ostatní",
      "city": "",
      "region": "Neznámý kraj",
      "address": "",
      "petrol_95": 39.45,
      "diesel": 37.8,
      "last_updated": "2026-06-27",
      "id": 13
    },
    {
      "name": "Zlínský kraj",
      "chain": "Ostatní",
      "city": "",
      "region": "Zlínský",
      "address": "",
      "petrol_95": 38.93,
      "diesel": 36.47,
      "last_updated": "2026-06-27",
      "id": 14
    },
    {
      "name": "Dnes",
      "chain": "Ostatní",
      "city": "",
      "region": "Neznámý kraj",
      "address": "",
      "petrol_95": 39.47,
      "diesel": 37.11,
      "last_updated": "2026-06-27",
      "id": 15
    },
    {
      "name": "Včera",
      "chain": "Ostatní",
      "city": "",
      "region": "Neznámý kraj",
      "address": "",
      "petrol_95": 39.51,
      "diesel": 37.25,
      "last_updated": "2026-06-27",
      "id": 16
    }
  ]
}